docx_edit_server/__init__.py
docx_edit_server/__main__.py
docx_edit_server/server.py
docx_edit_server/pyarmor_runtime_000000/__init__.py
docx_edit_server/pyarmor_runtime_000000/darwin_universal/pyarmor_runtime.so
iflow_mcp_docx_edit_server-0.1.3.dist-info/METADATA
iflow_mcp_docx_edit_server-0.1.3.dist-info/WHEEL
iflow_mcp_docx_edit_server-0.1.3.dist-info/entry_points.txt
iflow_mcp_docx_edit_server-0.1.3.dist-info/licenses/LICENSE
iflow_mcp_docx_edit_server-0.1.3.dist-info/RECORD
