Metadata-Version: 2.4
Name: iflow-mcp_docx-edit-server
Version: 0.1.3
Summary: A Model Context Protocol server providing docx edit capability
Author: iflow team
License: MIT
License-File: LICENSE
Keywords: automation,docx,llm,mcp
Classifier: Development Status :: 4 - Beta
Classifier: Intended Audience :: Developers
Classifier: License :: OSI Approved :: MIT License
Classifier: Programming Language :: Python :: 3
Classifier: Programming Language :: Python :: 3.10
Classifier: Programming Language :: Python :: 3.11
Classifier: Programming Language :: Python :: 3.12
Requires-Python: ==3.12.7
Requires-Dist: mcp[cli]>=1.12.4
Requires-Dist: pillow>=11.3.0
Requires-Dist: python-docx>=1.2.0
